mct/__init__.py
mct/__version__.py
mct/components_loader.py
mct/reconstruction.py
mct/utils.py
mct/cli_scripts/__init__.py
mct/cli_scripts/mct_calculate_noise_covariance_matrix.py
mct/cli_scripts/mct_calculate_tnsr.py
mct/cli_scripts/mct_combine_weighted_sum.py
mct/cli_scripts/mct_list_devices.py
mct/cli_scripts/mct_list_methods.py
mct/cli_scripts/mct_method_info.py
mct/cli_scripts/mct_reconstruct.py
mct/cli_scripts/mct_split_volumes.py
mct/reconstruction_methods/STARC.py
mct/reconstruction_methods/__init__.py
mct/reconstruction_methods/rCovSoS.py
mct/reconstruction_methods/rSoS.py
mct-0.3.2.dist-info/DESCRIPTION.rst
mct-0.3.2.dist-info/METADATA
mct-0.3.2.dist-info/RECORD
mct-0.3.2.dist-info/WHEEL
mct-0.3.2.dist-info/entry_points.txt
mct-0.3.2.dist-info/metadata.json
mct-0.3.2.dist-info/top_level.txt
tests/__init__.py
tests/test_mct.py
