Metadata-Version: 2.0
Name: mct
Version: 0.3.2
Summary: The MRI Coil-reconstruct Toolbox
Home-page: https://github.com/robbert-harms/mct
Author: Robbert Harms
Author-email: robbert@xkls.nl
Maintainer: Robbert Harms
Maintainer-email: robbert@xkls.nl
License: LGPL v3
Keywords: mct
Platform: UNKNOWN
Classifier: Environment :: Console
Classifier: Environment :: X11 Applications :: Qt
Classifier: Intended Audience :: Developers
Classifier: Intended Audience :: Science/Research
Classifier: License :: OSI Approved :: GNU Lesser General Public License v3 or later (LGPLv3+)
Classifier: Development Status :: 5 - Production/Stable
Classifier: Natural Language :: English
Classifier: Operating System :: POSIX :: Linux
Classifier: Operating System :: MacOS :: MacOS X
Classifier: Operating System :: Microsoft :: Windows
Classifier: Programming Language :: Python :: 3
Classifier: Programming Language :: Python :: 3.4
Classifier: Programming Language :: Python :: 3.5
Classifier: Programming Language :: Python :: 3.6
Classifier: Topic :: Scientific/Engineering
Requires-Dist: argcomplete
Requires-Dist: mdt (>=1.2.3)
Requires-Dist: mot (>=0.11.2)
Requires-Dist: nibabel
Requires-Dist: numpy
Requires-Dist: pyyaml
